ready_set_deploy/__init__.py
ready_set_deploy/cli.py
ready_set_deploy/components.py
ready_set_deploy/config.py
ready_set_deploy/elements.py
ready_set_deploy/gatherers/base.py
ready_set_deploy/gatherers/homebrew.py
ready_set_deploy/gatherers/posixfile.py
ready_set_deploy/providers/files.py
ready_set_deploy/registry.py
ready_set_deploy/renderers/base.py
ready_set_deploy/renderers/homebrew.py
ready_set_deploy/runner.py
ready_set_deploy/systems.py
ready_set_deploy-1.0.0.dist-info/entry_points.txt
ready_set_deploy-1.0.0.dist-info/WHEEL
ready_set_deploy-1.0.0.dist-info/METADATA
ready_set_deploy-1.0.0.dist-info/RECORD
