Metadata-Version: 2.1
Name: ready-set-deploy
Version: 1.0.0
Summary: Ready-set-deploy is a deployment framework designed to be offline-first 
License: MIT
Author: Steven Karas
Author-email: steven.karas@gmail.com
Requires-Python: >=3.9,<4.0
Classifier: License :: OSI Approved :: MIT License
Classifier: Programming Language :: Python :: 3
Classifier: Programming Language :: Python :: 3.9
Requires-Dist: click (>=8.0.4,<9.0.0)
Requires-Dist: more-itertools (>=8.12.0,<9.0.0)
Requires-Dist: tomli (>=2.0.1,<3.0.0)
